LICENSE
MANIFEST.in
README.md
setup.py
demo/manage.py
demo/requirements.txt
demo/demo/__init__.py
demo/demo/settings.py
demo/demo/urls.py
demo/demo/views.py
demo/demo/wsgi.py
demo/demo/templates/index.html
demo/demo/templates/success.html
django_nocaptcha_recaptcha.egg-info/PKG-INFO
django_nocaptcha_recaptcha.egg-info/SOURCES.txt
django_nocaptcha_recaptcha.egg-info/dependency_links.txt
django_nocaptcha_recaptcha.egg-info/not-zip-safe
django_nocaptcha_recaptcha.egg-info/top_level.txt
nocaptcha_recaptcha/__init__.py
nocaptcha_recaptcha/_compat.py
nocaptcha_recaptcha/client.py
nocaptcha_recaptcha/fields.py
nocaptcha_recaptcha/models.py
nocaptcha_recaptcha/tests.py
nocaptcha_recaptcha/views.py
nocaptcha_recaptcha/widgets.py
nocaptcha_recaptcha/templates/nocaptcha_recaptcha/widget.html