Metadata-Version: 1.1
Name: django-nocaptcha-recaptcha
Version: 0.0.20
Summary: Django nocaptcha recaptcha form field/widget app.
Home-page: https://github.com/ImaginaryLandscape/django-nocaptcha-recaptcha
Author: Imaginary Landscape
Author-email: jjasinski@imgescape.com
License: BSD
Keywords: django,recaptcha,field,nocaptcha
Platform: UNKNOWN
Classifier: Framework :: Django
Classifier: License :: OSI Approved :: BSD License
Classifier: Operating System :: OS Independent
Classifier: Intended Audience :: Developers
Classifier: Programming Language :: Python :: 2.6
Classifier: Programming Language :: Python :: 2.7
Classifier: Programming Language :: Python :: 3.4
Classifier: Programming Language :: Python :: 3.5
Classifier: Programming Language :: Python :: 3.6
Classifier: Topic :: Internet :: WWW/HTTP :: Dynamic Content
